odoo/addons/sale_comment_template/README.rst
odoo/addons/sale_comment_template/__init__.py
odoo/addons/sale_comment_template/__manifest__.py
odoo/addons/sale_comment_template/i18n/de.po
odoo/addons/sale_comment_template/i18n/es.po
odoo/addons/sale_comment_template/i18n/fr.po
odoo/addons/sale_comment_template/i18n/it.po
odoo/addons/sale_comment_template/i18n/pt.po
odoo/addons/sale_comment_template/i18n/sale_comment_template.pot
odoo/addons/sale_comment_template/migrations/13.0.1.0.0/post-migration.py
odoo/addons/sale_comment_template/migrations/13.0.1.0.0/pre-migration.py
odoo/addons/sale_comment_template/models/__init__.py
odoo/addons/sale_comment_template/models/sale_order.py
odoo/addons/sale_comment_template/readme/CONTRIBUTORS.rst
odoo/addons/sale_comment_template/readme/DESCRIPTION.rst
odoo/addons/sale_comment_template/readme/INSTALL.rst
odoo/addons/sale_comment_template/security/ir.model.access.csv
odoo/addons/sale_comment_template/static/description/icon.png
odoo/addons/sale_comment_template/static/description/index.html
odoo/addons/sale_comment_template/tests/__init__.py
odoo/addons/sale_comment_template/tests/test_sale_order_report.py
odoo/addons/sale_comment_template/views/base_comment_template_view.xml
odoo/addons/sale_comment_template/views/report_saleorder.xml
odoo/addons/sale_comment_template/views/sale_order_view.xml
odoo13_addon_sale_comment_template-13.0.1.0.1.dev4.dist-info/METADATA
odoo13_addon_sale_comment_template-13.0.1.0.1.dev4.dist-info/WHEEL
odoo13_addon_sale_comment_template-13.0.1.0.1.dev4.dist-info/top_level.txt
odoo13_addon_sale_comment_template-13.0.1.0.1.dev4.dist-info/RECORD
